codon_genie/__init__.py
codon_genie/client.py
codon_genie/codon_selector.py
codon_genie/codon_utils.py
codon_genie/ncbi_tax_utils.py
codon_genie/seq_utils.py
codon_genie/example/__init__.py
codon_genie/example/align.py
codon_genie/test/__init__.py
codon_genie/test/test_client.py
codon_genie/test/test_codon_genie.py
CodonGenie-1.7.dist-info/LICENSE
CodonGenie-1.7.dist-info/METADATA
CodonGenie-1.7.dist-info/WHEEL
CodonGenie-1.7.dist-info/top_level.txt
CodonGenie-1.7.dist-info/RECORD
