Metadata-Version: 2.1
Name: CodonGenie
Version: 1.7
Summary: CodonGenie
Home-page: https://github.com/neilswainston/CodonGenie
Author: Neil Swainston
Author-email: neil.swainston@liverpool.ac.uk
License: UNKNOWN
Platform: UNKNOWN
Classifier: Programming Language :: Python :: 3
Classifier: License :: OSI Approved :: MIT License
Classifier: Operating System :: OS Independent
Requires-Python: >=3.7
